{"accumulated": [{"days": 7, "sum_of_share_squared": 0.027785426217466873, "vcount": 555, "plus_rshares": 139846195724027.0, "minus_rshares": 13940211887422.0, "dnvotee_count": 22, "self_rshares": 0, "upvotee": [{"rshares": 17647716274179, "account": "sanha88", "percentage": 12.62}, {"rshares": 5703285831555, "account": "granturismo", "percentage": 4.08}, {"rshares": 4127528486708, "account": "sindorimspinoza", "percentage": 2.95}, {"rshares": 4079165367224, "account": "hermes-k", "percentage": 2.92}, {"rshares": 3246148018894, "account": "rothbardianism", "percentage": 2.32}, {"rshares": 3245092147589, "account": "pius.pius", "percentage": 2.32}, {"rshares": 3104742578341, "account": "vixima7", "percentage": 2.22}, {"rshares": 2975672359450, "account": "joeuhw", "percentage": 2.13}, {"rshares": 2814996523599, "account": "kr-marketing", "percentage": 2.01}, {"rshares": 2750021394647, "account": "solafide7981", "percentage": 1.97}], "downvotee": [{"rshares": 5841734613338, "account": "kcelebs", "percentage": 41.91}, {"rshares": 1591900606950, "account": "lexio", "percentage": 11.42}, {"rshares": 1374977194243, "account": "xarion94", "percentage": 9.86}, {"rshares": 1060904857659, "account": "anaita94", "percentage": 7.61}, {"rshares": 866089694010, "account": "electrogordo", "percentage": 6.21}, {"rshares": 616906815426, "account": "ccrystal", "percentage": 4.43}, {"rshares": 509171397136, "account": "malex30", "percentage": 3.65}, {"rshares": 357502514425, "account": "aslan1", "percentage": 2.56}, {"rshares": 291980247494, "account": "steemit2015", "percentage": 2.09}, {"rshares": 227487206471, "account": "gentecomun", "percentage": 1.63}], "self_vote_rate": 0.0, "avg_full_voting_per_day": 9.72, "dnvcount": 126, "start_date": "2018-04-12", "all_vweight": 680400.0, "upvcount": 429, "upvotee_count": 184, "end_date": "2018-04-19", "inverse_simpson": 36}, {"days": 14, "sum_of_share_squared": 0.026832864266905017, "vcount": 1008, "plus_rshares": 288527195429594.0, "minus_rshares": 18604912275748.0, "dnvotee_count": 33, "self_rshares": 0, "upvotee": [{"rshares": 36540642492042, "account": "sanha88", "percentage": 12.66}, {"rshares": 9603659686298, "account": "granturismo", "percentage": 3.33}, {"rshares": 9392599770531, "account": "mmerlin", "percentage": 3.26}, {"rshares": 8716953291114, "account": "sindorimspinoza", "percentage": 3.02}, {"rshares": 8138161321515, "account": "pius.pius", "percentage": 2.82}, {"rshares": 7577187947971, "account": "joeuhw", "percentage": 2.63}, {"rshares": 7146606269809, "account": "hermes-k", "percentage": 2.48}, {"rshares": 6842725968631, "account": "kr-marketing", "percentage": 2.37}, {"rshares": 5686808489686, "account": "carrotcake", "percentage": 1.97}, {"rshares": 5339864404836, "account": "asbear", "percentage": 1.85}], "downvotee": [{"rshares": 5841734613338, "account": "kcelebs", "percentage": 31.4}, {"rshares": 1879193750511, "account": "steemit2015", "percentage": 10.1}, {"rshares": 1591900606950, "account": "lexio", "percentage": 8.56}, {"rshares": 1374977194243, "account": "xarion94", "percentage": 7.39}, {"rshares": 1133797088273, "account": "german2015", "percentage": 6.09}, {"rshares": 1122964369890, "account": "blackpace", "percentage": 6.04}, {"rshares": 1060904857659, "account": "anaita94", "percentage": 5.7}, {"rshares": 866089694010, "account": "electrogordo", "percentage": 4.66}, {"rshares": 616906815426, "account": "ccrystal", "percentage": 3.32}, {"rshares": 509171397136, "account": "malex30", "percentage": 2.74}], "self_vote_rate": 0.0, "avg_full_voting_per_day": 10.31, "dnvcount": 181, "start_date": "2018-04-05", "all_vweight": 1444000.0, "upvcount": 827, "upvotee_count": 262, "end_date": "2018-04-19", "inverse_simpson": 37}, {"days": 30, "sum_of_share_squared": 0.022793606018786983, "vcount": 2206, "plus_rshares": 560473001456592.0, "minus_rshares": 64529231859222.0, "dnvotee_count": 89, "self_rshares": 1591492208272.0, "upvotee": [{"rshares": 63372012363116, "account": "sanha88", "percentage": 11.31}, {"rshares": 19115772446385, "account": "granturismo", "percentage": 3.41}, {"rshares": 16291677741265, "account": "ravenclaw69", "percentage": 2.91}, {"rshares": 16097181581614, "account": "joeuhw", "percentage": 2.87}, {"rshares": 15367897204840, "account": "sindorimspinoza", "percentage": 2.74}, {"rshares": 14554266358301, "account": "mmerlin", "percentage": 2.6}, {"rshares": 12293956770033, "account": "kr-marketing", "percentage": 2.19}, {"rshares": 11242732039453, "account": "rothbardianism", "percentage": 2.01}, {"rshares": 11224579269947, "account": "armdown", "percentage": 2.0}, {"rshares": 10104047212535, "account": "asbear", "percentage": 1.8}], "downvotee": [{"rshares": 19039922166397, "account": "adeotidaniel", "percentage": 29.51}, {"rshares": 9251364588145, "account": "cinta01", "percentage": 14.34}, {"rshares": 5841734613338, "account": "kcelebs", "percentage": 9.05}, {"rshares": 3275817858185, "account": "betesda", "percentage": 5.08}, {"rshares": 2651084310866, "account": "ansony", "percentage": 4.11}, {"rshares": 2023765279467, "account": "xtreme2015", "percentage": 3.14}, {"rshares": 1922264172811, "account": "steemit2015", "percentage": 2.98}, {"rshares": 1591900606950, "account": "lexio", "percentage": 2.47}, {"rshares": 1435292161571, "account": "blackpace", "percentage": 2.22}, {"rshares": 1374977194243, "account": "xarion94", "percentage": 2.13}], "self_vote_rate": 0.28, "avg_full_voting_per_day": 8.9, "dnvcount": 434, "start_date": "2018-03-20", "all_vweight": 2669000.0, "upvcount": 1772, "upvotee_count": 424, "end_date": "2018-04-19", "inverse_simpson": 44}, {"days": 60, "sum_of_share_squared": 0.02008467597017238, "vcount": 4736, "plus_rshares": 1047364622230963.0, "minus_rshares": 213298661064090.0, "dnvotee_count": 135, "self_rshares": 1859102799231.0, "upvotee": [{"rshares": 113516866025789, "account": "sanha88", "percentage": 10.84}, {"rshares": 44715686047635, "account": "granturismo", "percentage": 4.27}, {"rshares": 26327174922377, "account": "ravenclaw69", "percentage": 2.51}, {"rshares": 25309407951163, "account": "rothbardianism", "percentage": 2.42}, {"rshares": 24883960130506, "account": "joeuhw", "percentage": 2.38}, {"rshares": 20167211233416, "account": "mmerlin", "percentage": 1.93}, {"rshares": 18100521710333, "account": "thinky", "percentage": 1.73}, {"rshares": 17689076089491, "account": "armdown", "percentage": 1.69}, {"rshares": 15742786947288, "account": "sindorimspinoza", "percentage": 1.5}, {"rshares": 15609302285004, "account": "kr-marketing", "percentage": 1.49}], "downvotee": [{"rshares": 40404876904811, "account": "soniia", "percentage": 18.94}, {"rshares": 32994285887006, "account": "shikto", "percentage": 15.47}, {"rshares": 24183010514361, "account": "ruponti", "percentage": 11.34}, {"rshares": 19039922166397, "account": "adeotidaniel", "percentage": 8.93}, {"rshares": 15002407054830, "account": "shanto62", "percentage": 7.03}, {"rshares": 11395486036581, "account": "greatstory", "percentage": 5.34}, {"rshares": 9251364588145, "account": "cinta01", "percentage": 4.34}, {"rshares": 6174527068166, "account": "engrbrain1", "percentage": 2.89}, {"rshares": 5841734613338, "account": "kcelebs", "percentage": 2.74}, {"rshares": 3275817858185, "account": "betesda", "percentage": 1.54}], "self_vote_rate": 0.18, "avg_full_voting_per_day": 6.2, "dnvcount": 912, "start_date": "2018-02-18", "all_vweight": 3720100.0, "upvcount": 3824, "upvotee_count": 743, "end_date": "2018-04-19", "inverse_simpson": 50}, {"days": 90, "sum_of_share_squared": 0.014822878201538896, "vcount": 6589, "plus_rshares": 1559455879715302.0, "minus_rshares": 293720621345406.0, "dnvotee_count": 162, "self_rshares": 58294168252387.0, "upvotee": [{"rshares": 113516866025789, "account": "sanha88", "percentage": 7.28}, {"rshares": 79432444618758, "account": "granturismo", "percentage": 5.09}, {"rshares": 58294168252387, "account": "noctisk", "percentage": 3.74}, {"rshares": 36241603089759, "account": "joeuhw", "percentage": 2.32}, {"rshares": 30153251796210, "account": "index765", "percentage": 1.93}, {"rshares": 28590799310534, "account": "krexchange", "percentage": 1.83}, {"rshares": 26327174922377, "account": "ravenclaw69", "percentage": 1.69}, {"rshares": 25309407951163, "account": "rothbardianism", "percentage": 1.62}, {"rshares": 24184563022771, "account": "devpark", "percentage": 1.55}, {"rshares": 20316139830936, "account": "mmerlin", "percentage": 1.3}], "downvotee": [{"rshares": 50287601108735, "account": "abdsamadsakhi", "percentage": 17.12}, {"rshares": 40404876904811, "account": "soniia", "percentage": 13.76}, {"rshares": 32994285887006, "account": "shikto", "percentage": 11.23}, {"rshares": 24183010514361, "account": "ruponti", "percentage": 8.23}, {"rshares": 23786931456870, "account": "kimjunghyun", "percentage": 8.1}, {"rshares": 19039922166397, "account": "adeotidaniel", "percentage": 6.48}, {"rshares": 15002407054830, "account": "shanto62", "percentage": 5.11}, {"rshares": 11395486036581, "account": "greatstory", "percentage": 3.88}, {"rshares": 9251364588145, "account": "cinta01", "percentage": 3.15}, {"rshares": 6174527068166, "account": "engrbrain1", "percentage": 2.1}], "self_vote_rate": 3.74, "avg_full_voting_per_day": 6.99, "dnvcount": 1185, "start_date": "2018-01-19", "all_vweight": 6290200.0, "upvcount": 5404, "upvotee_count": 993, "end_date": "2018-04-19", "inverse_simpson": 67}], "weekly": [{"days": 7, "sum_of_share_squared": 0.027785426217466873, "vcount": 555, "plus_rshares": 139846195724027.0, "minus_rshares": 13940211887422.0, "dnvotee_count": 22, "self_rshares": 0, "upvotee": [{"rshares": 17647716274179, "account": "sanha88", "percentage": 12.62}, {"rshares": 5703285831555, "account": "granturismo", "percentage": 4.08}, {"rshares": 4127528486708, "account": "sindorimspinoza", "percentage": 2.95}, {"rshares": 4079165367224, "account": "hermes-k", "percentage": 2.92}, {"rshares": 3246148018894, "account": "rothbardianism", "percentage": 2.32}, {"rshares": 3245092147589, "account": "pius.pius", "percentage": 2.32}, {"rshares": 3104742578341, "account": "vixima7", "percentage": 2.22}, {"rshares": 2975672359450, "account": "joeuhw", "percentage": 2.13}, {"rshares": 2814996523599, "account": "kr-marketing", "percentage": 2.01}, {"rshares": 2750021394647, "account": "solafide7981", "percentage": 1.97}], "downvotee": [{"rshares": 5841734613338, "account": "kcelebs", "percentage": 41.91}, {"rshares": 1591900606950, "account": "lexio", "percentage": 11.42}, {"rshares": 1374977194243, "account": "xarion94", "percentage": 9.86}, {"rshares": 1060904857659, "account": "anaita94", "percentage": 7.61}, {"rshares": 866089694010, "account": "electrogordo", "percentage": 6.21}, {"rshares": 616906815426, "account": "ccrystal", "percentage": 4.43}, {"rshares": 509171397136, "account": "malex30", "percentage": 3.65}, {"rshares": 357502514425, "account": "aslan1", "percentage": 2.56}, {"rshares": 291980247494, "account": "steemit2015", "percentage": 2.09}, {"rshares": 227487206471, "account": "gentecomun", "percentage": 1.63}], "self_vote_rate": 0.0, "avg_full_voting_per_day": 9.72, "dnvcount": 126, "start_date": "2018-04-12", "all_vweight": 680400.0, "upvcount": 429, "upvotee_count": 184, "end_date": "2018-04-19", "inverse_simpson": 36}, {"days": 7, "sum_of_share_squared": 0.029041088920187728, "vcount": 453, "plus_rshares": 148680999705567.0, "minus_rshares": 4664700388326.0, "dnvotee_count": 14, "self_rshares": 0, "upvotee": [{"rshares": 18892926217863, "account": "sanha88", "percentage": 12.71}, {"rshares": 6718478736298, "account": "mmerlin", "percentage": 4.52}, {"rshares": 4893069173926, "account": "pius.pius", "percentage": 3.29}, {"rshares": 4601515588521, "account": "joeuhw", "percentage": 3.09}, {"rshares": 4589424804406, "account": "sindorimspinoza", "percentage": 3.09}, {"rshares": 4027729445032, "account": "kr-marketing", "percentage": 2.71}, {"rshares": 3900373854743, "account": "granturismo", "percentage": 2.62}, {"rshares": 3716667739338, "account": "ravenclaw69", "percentage": 2.5}, {"rshares": 3705005891855, "account": "carrotcake", "percentage": 2.49}, {"rshares": 3067440902585, "account": "hermes-k", "percentage": 2.06}], "downvotee": [{"rshares": 1587213503017, "account": "steemit2015", "percentage": 34.03}, {"rshares": 1133797088273, "account": "german2015", "percentage": 24.31}, {"rshares": 1122964369890, "account": "blackpace", "percentage": 24.07}, {"rshares": 259057578527, "account": "sky2sky", "percentage": 5.55}, {"rshares": 194548156241, "account": "marcelof", "percentage": 4.17}, {"rshares": 97147489419, "account": "aliwali", "percentage": 2.08}, {"rshares": 97147489419, "account": "balia", "percentage": 2.08}, {"rshares": 43196451467, "account": "kally", "percentage": 0.93}, {"rshares": 21617386788, "account": "armia", "percentage": 0.46}, {"rshares": 21617386788, "account": "hendrazal97", "percentage": 0.46}], "self_vote_rate": 0.0, "avg_full_voting_per_day": 10.91, "dnvcount": 55, "start_date": "2018-04-05", "all_vweight": 763600.0, "upvcount": 398, "upvotee_count": 177, "end_date": "2018-04-12", "inverse_simpson": 34}, {"days": 7, "sum_of_share_squared": 0.02611226082505069, "vcount": 438, "plus_rshares": 136976542226555.0, "minus_rshares": 6596270072285.0, "dnvotee_count": 21, "self_rshares": 0, "upvotee": [{"rshares": 13165648516268, "account": "sanha88", "percentage": 9.61}, {"rshares": 6693032489069, "account": "ravenclaw69", "percentage": 4.89}, {"rshares": 6650943913726, "account": "sindorimspinoza", "percentage": 4.86}, {"rshares": 5809783491016, "account": "granturismo", "percentage": 4.24}, {"rshares": 5668230649766, "account": "biba1029", "percentage": 4.14}, {"rshares": 4259520885280, "account": "joeuhw", "percentage": 3.11}, {"rshares": 3646587425855, "account": "carrotcake", "percentage": 2.66}, {"rshares": 3569395352739, "account": "kr-marketing", "percentage": 2.61}, {"rshares": 3536044267496, "account": "rothbardianism", "percentage": 2.58}, {"rshares": 3138329797195, "account": "mmerlin", "percentage": 2.29}], "downvotee": [{"rshares": 3232747435885, "account": "betesda", "percentage": 49.01}, {"rshares": 668533600591, "account": "sky2sky", "percentage": 10.14}, {"rshares": 485105718411, "account": "balia", "percentage": 7.35}, {"rshares": 431092956566, "account": "syeinoi", "percentage": 6.54}, {"rshares": 388047153420, "account": "xtreme2015", "percentage": 5.88}, {"rshares": 312569347333, "account": "danylives", "percentage": 4.74}, {"rshares": 204814209440, "account": "sakhisamid", "percentage": 3.11}, {"rshares": 183207265722, "account": "vfestjhjt", "percentage": 2.78}, {"rshares": 107796952337, "account": "richardgerald", "percentage": 1.63}, {"rshares": 97116144715, "account": "vanessa2015", "percentage": 1.47}], "self_vote_rate": 0.0, "avg_full_voting_per_day": 10.03, "dnvcount": 66, "start_date": "2018-03-29", "all_vweight": 701900.0, "upvcount": 372, "upvotee_count": 162, "end_date": "2018-04-05", "inverse_simpson": 38}, {"days": 7, "sum_of_share_squared": 0.025133836708739494, "vcount": 581, "plus_rshares": 110315065480896.0, "minus_rshares": 20030171782041.0, "dnvotee_count": 48, "self_rshares": 1591492208272.0, "upvotee": [{"rshares": 11924709501146, "account": "sanha88", "percentage": 10.81}, {"rshares": 4745728778216, "account": "armdown", "percentage": 4.3}, {"rshares": 4703421146049, "account": "ravenclaw69", "percentage": 4.26}, {"rshares": 3702329269071, "account": "granturismo", "percentage": 3.36}, {"rshares": 3401815155484, "account": "afinesword", "percentage": 3.08}, {"rshares": 3185784536007, "account": "joeuhw", "percentage": 2.89}, {"rshares": 2895064249306, "account": "rothbardianism", "percentage": 2.62}, {"rshares": 2118927676082, "account": "otac", "percentage": 1.92}, {"rshares": 2109335484015, "account": "kimthewriter", "percentage": 1.91}, {"rshares": 2023812752653, "account": "banguri", "percentage": 1.83}], "downvotee": [{"rshares": 9251364588145, "account": "cinta01", "percentage": 46.19}, {"rshares": 2359114450041, "account": "ansony", "percentage": 11.78}, {"rshares": 1377762563296, "account": "xtreme2015", "percentage": 6.88}, {"rshares": 667643324892, "account": "good-instagram", "percentage": 3.33}, {"rshares": 635412870046, "account": "haiza", "percentage": 3.17}, {"rshares": 581138809773, "account": "vfestjhjt", "percentage": 2.9}, {"rshares": 570798524941, "account": "abangace99", "percentage": 2.85}, {"rshares": 409251772599, "account": "mifta23", "percentage": 2.04}, {"rshares": 387538248756, "account": "vanessa2015", "percentage": 1.93}, {"rshares": 323076081365, "account": "lolitata", "percentage": 1.61}], "self_vote_rate": 1.44, "avg_full_voting_per_day": 7.06, "dnvcount": 172, "start_date": "2018-03-22", "all_vweight": 494500.0, "upvcount": 409, "upvotee_count": 192, "end_date": "2018-03-29", "inverse_simpson": 40}, {"days": 7, "sum_of_share_squared": 0.03497477108425601, "vcount": 646, "plus_rshares": 119391594187928.0, "minus_rshares": 38565319314315.0, "dnvotee_count": 20, "self_rshares": 0, "upvotee": [{"rshares": 16965964989980, "account": "thinky", "percentage": 14.21}, {"rshares": 9866786169272, "account": "sanha88", "percentage": 8.26}, {"rshares": 3606021563571, "account": "granturismo", "percentage": 3.02}, {"rshares": 3595881478229, "account": "ravenclaw69", "percentage": 3.01}, {"rshares": 3382028319278, "account": "joeuhw", "percentage": 2.83}, {"rshares": 3220390407103, "account": "joey0513", "percentage": 2.7}, {"rshares": 2587552690962, "account": "creamer7", "percentage": 2.17}, {"rshares": 2135935627194, "account": "dakfn", "percentage": 1.79}, {"rshares": 1921584477688, "account": "mmerlin", "percentage": 1.61}, {"rshares": 1889786818546, "account": "banjjakism", "percentage": 1.58}], "downvotee": [{"rshares": 19039922166397, "account": "adeotidaniel", "percentage": 49.37}, {"rshares": 11395486036581, "account": "greatstory", "percentage": 29.55}, {"rshares": 1396283207736, "account": "steembidbot", "percentage": 3.62}, {"rshares": 1364061287558, "account": "msp-bidbot", "percentage": 3.54}, {"rshares": 1331839367379, "account": "allaz", "percentage": 3.45}, {"rshares": 1278136167082, "account": "minnowhelper", "percentage": 3.31}, {"rshares": 1256654886963, "account": "soysoy", "percentage": 3.26}, {"rshares": 419003362543, "account": "xtreme2015", "percentage": 1.09}, {"rshares": 300418035414, "account": "rajeeb", "percentage": 0.78}, {"rshares": 193161315590, "account": "adedejioshi", "percentage": 0.5}], "self_vote_rate": 0.0, "avg_full_voting_per_day": 6.16, "dnvcount": 115, "start_date": "2018-03-15", "all_vweight": 430900.0, "upvcount": 531, "upvotee_count": 251, "end_date": "2018-03-22", "inverse_simpson": 29}, {"days": 7, "sum_of_share_squared": 0.022402878827016984, "vcount": 673, "plus_rshares": 138760113040926.0, "minus_rshares": 8082637190731.0, "dnvotee_count": 10, "self_rshares": 171514640776.0, "upvotee": [{"rshares": 14916026961911, "account": "sanha88", "percentage": 10.75}, {"rshares": 6419104424297, "account": "ravenclaw69", "percentage": 4.63}, {"rshares": 5432296649611, "account": "granturismo", "percentage": 3.91}, {"rshares": 3493147774723, "account": "artshop", "percentage": 2.52}, {"rshares": 2871692125891, "account": "creamer7", "percentage": 2.07}, {"rshares": 2808510121812, "account": "hermes-k", "percentage": 2.02}, {"rshares": 2806821882006, "account": "virus707", "percentage": 2.02}, {"rshares": 2764617424700, "account": "banjjakism", "percentage": 1.99}, {"rshares": 2507223464619, "account": "wansoon16", "percentage": 1.81}, {"rshares": 2195892611923, "account": "rothbardianism", "percentage": 1.58}], "downvotee": [{"rshares": 6174527068166, "account": "engrbrain1", "percentage": 76.39}, {"rshares": 611019152346, "account": "amry", "percentage": 7.56}, {"rshares": 536248549229, "account": "alvinkei", "percentage": 6.63}, {"rshares": 192930701780, "account": "mirdha", "percentage": 2.39}, {"rshares": 171536045943, "account": "good-instagram", "percentage": 2.12}, {"rshares": 96440894362, "account": "meh12", "percentage": 1.19}, {"rshares": 96395765541, "account": "fahrisukses93", "percentage": 1.19}, {"rshares": 96343937158, "account": "teakwood", "percentage": 1.19}, {"rshares": 85780625086, "account": "tomasbonillo", "percentage": 1.06}, {"rshares": 21414451120, "account": "sakhisamid", "percentage": 0.26}], "self_vote_rate": 0.12, "avg_full_voting_per_day": 10.27, "dnvcount": 49, "start_date": "2018-03-08", "all_vweight": 719000.0, "upvcount": 624, "upvotee_count": 275, "end_date": "2018-03-15", "inverse_simpson": 45}, {"days": 7, "sum_of_share_squared": 0.02112223511130154, "vcount": 663, "plus_rshares": 139699055264672.0, "minus_rshares": 4974265485301.0, "dnvotee_count": 13, "self_rshares": 64143001589.0, "upvotee": [{"rshares": 12225152322443, "account": "sanha88", "percentage": 8.75}, {"rshares": 7336186391483, "account": "granturismo", "percentage": 5.25}, {"rshares": 5369488903437, "account": "euijin", "percentage": 3.84}, {"rshares": 3679837078708, "account": "mooyeobpark", "percentage": 2.63}, {"rshares": 3572341153133, "account": "index765", "percentage": 2.56}, {"rshares": 3357924410857, "account": "rothbardianism", "percentage": 2.4}, {"rshares": 3346485225353, "account": "armdown", "percentage": 2.4}, {"rshares": 3238285884841, "account": "ganzi", "percentage": 2.32}, {"rshares": 3198837590543, "account": "tintom", "percentage": 2.29}, {"rshares": 2963595641383, "account": "kmlee", "percentage": 2.12}], "downvotee": [{"rshares": 1712449856009, "account": "sakhisamid", "percentage": 34.43}, {"rshares": 983585593111, "account": "lucyexactly12345", "percentage": 19.77}, {"rshares": 866545639145, "account": "meh12", "percentage": 17.42}, {"rshares": 385177933528, "account": "good-instagram", "percentage": 7.74}, {"rshares": 213823539970, "account": "krani7", "percentage": 4.3}, {"rshares": 192635668904, "account": "coin104", "percentage": 3.87}, {"rshares": 192451190978, "account": "abdsamadsakhi", "percentage": 3.87}, {"rshares": 171058831976, "account": "cexmad", "percentage": 3.44}, {"rshares": 96220592986, "account": "ami18", "percentage": 1.93}, {"rshares": 96162672262, "account": "dkgautam", "percentage": 1.93}], "self_vote_rate": 0.05, "avg_full_voting_per_day": 10.4, "dnvcount": 107, "start_date": "2018-03-01", "all_vweight": 728100.0, "upvcount": 556, "upvotee_count": 222, "end_date": "2018-03-08", "inverse_simpson": 47}], "account": {"savings_sbd_last_interest_payment": "1970-01-01T00:00:00", "last_bandwidth_update": "2018-04-19T07:14:54", "post_count": 2342, "reward_sbd_balance": "0.000 SBD", "lifetime_bandwidth": "4385564000000", "witness_votes": [], "last_root_post": "2018-04-18T12:33:03", "sbd_seconds": "1722466535451", "reset_account": "null", "name": "noctisk", "tags_usage": [], "json_metadata": "{\"profile\":{\"name\":\"\ubc31\ud654\uc120\uc0dd\",\"about\":\"The \u201c\uc7a1\ud559\u201d Curator\",\"location\":\"Seoul, Korea\",\"profile_image\":\"https://i.imgsafe.org/3d/3d95b91a9d.jpeg\",\"cover_image\":\"https://i.imgsafe.org/3d/3d95ba5176.jpeg\"}}", "delegated_vesting_shares": "0.000000 VESTS", "vesting_balance": "0.000 STEEM", "proxied_vsf_votes": [1083229084, 0, 0, 0], "last_market_bandwidth_update": "2018-04-15T01:08:30", "id": 448726, "savings_sbd_balance": "0.000 SBD", "curation_rewards": 571470, "last_account_recovery": "1970-01-01T00:00:00", "average_market_bandwidth": "9717201389", "mined": false, "received_vesting_shares": "100000000.000000 VESTS", "sbd_last_interest_payment": "2018-04-05T06:51:42", "savings_sbd_seconds": "0", "voting_power": 7753, "withdrawn": 0, "reward_vesting_balance": "1764.707313 VESTS", "vesting_shares": "8337643.054069 VESTS", "post_history": [], "reward_steem_balance": "0.000 STEEM", "sbd_balance": "1565.750 SBD", "last_post": "2018-04-19T07:14:54", "recovery_account": "steem", "lifetime_vote_count": 0, "proxy": "clayop", "to_withdraw": "8224317758328", "reward_vesting_steem": "0.866 STEEM", "savings_withdraw_requests": 0, "next_vesting_withdrawal": "2018-04-23T02:24:00", "last_vote_time": "2018-04-19T05:47:03", "withdraw_routes": 0, "lifetime_market_bandwidth": "154270000000", "savings_sbd_seconds_last_update": "1970-01-01T00:00:00", "transfer_history": [], "average_bandwidth": "186208431048", "comment_count": 0, "other_history": [], "can_vote": true, "savings_balance": "0.000 STEEM", "guest_bloggers": [], "vote_history": [], "witnesses_voted_for": 0, "reputation": "37673752062319", "last_account_update": "2018-02-18T04:08:15", "created": "2017-11-14T22:33:18", "sbd_seconds_last_update": "2018-04-19T05:26:36", "posting_rewards": 3333745, "vesting_withdraw_rate": "632639.827563 VESTS", "market_history": [], "balance": "0.000 STEEM", "last_owner_update": "2017-12-01T01:40:27"}}