{"accumulated": [{"start_date": "2018-03-29", "end_date": "2018-04-05", "days": 7, "all_vweight": 121000.0, "plus_rshares": 10475660931955.0, "minus_rshares": 0, "self_rshares": 0, "sum_of_share_squared": 0.10631367073012893, "vcount": 47, "inverse_simpson": 9, "avg_full_voting_per_day": 1.73, "upvcount": 47, "upvotee_count": 27, "dnvcount": 0, "dnvotee_count": 0, "self_vote_rate": 0.0, "upvotee": [{"account": "meesterboom", "percentage": 24.98, "rshares": 2616699589334}, {"account": "goldenoakfarm", "percentage": 13.67, "rshares": 1432455374589}, {"account": "therealpaul", "percentage": 9.56, "rshares": 1001425255658}, {"account": "writeous", "percentage": 6.65, "rshares": 696617063065}, {"account": "steemitri", "percentage": 4.11, "rshares": 431044885783}, {"account": "qberryfarms", "percentage": 3.33, "rshares": 348329655732}, {"account": "shadowspub", "percentage": 3.28, "rshares": 343955781021}, {"account": "countrygirl", "percentage": 3.24, "rshares": 339611122132}, {"account": "englishtchrivy", "percentage": 3.24, "rshares": 339611122132}, {"account": "jaybird", "percentage": 2.49, "rshares": 261247241800}], "downvotee": []}, {"start_date": "2018-03-22", "end_date": "2018-04-05", "days": 14, "all_vweight": 209200.0, "plus_rshares": 18144235532939.0, "minus_rshares": 0, "self_rshares": 0, "sum_of_share_squared": 0.11179810209788604, "vcount": 86, "inverse_simpson": 9, "avg_full_voting_per_day": 1.49, "upvcount": 86, "upvotee_count": 44, "dnvcount": 0, "dnvotee_count": 0, "self_vote_rate": 0.0, "upvotee": [{"account": "meesterboom", "percentage": 28.0, "rshares": 5080118132060}, {"account": "goldenoakfarm", "percentage": 13.44, "rshares": 2437750473849}, {"account": "therealpaul", "percentage": 6.24, "rshares": 1131991370467}, {"account": "writeous", "percentage": 5.76, "rshares": 1044904470398}, {"account": "papa-pepper", "percentage": 3.36, "rshares": 609267228487}, {"account": "englishtchrivy", "percentage": 2.83, "rshares": 513699275211}, {"account": "steemitri", "percentage": 2.38, "rshares": 431044885783}, {"account": "clio", "percentage": 1.97, "rshares": 356994592516}, {"account": "qberryfarms", "percentage": 1.92, "rshares": 348329655732}, {"account": "slowwalker", "percentage": 1.92, "rshares": 348287407333}], "downvotee": []}, {"start_date": "2018-03-06", "end_date": "2018-04-05", "days": 30, "all_vweight": 379600.0, "plus_rshares": 32928792716158.0, "minus_rshares": 0, "self_rshares": 2306020448904.0, "sum_of_share_squared": 0.10812650993752322, "vcount": 189, "inverse_simpson": 9, "avg_full_voting_per_day": 1.27, "upvcount": 189, "upvotee_count": 85, "dnvcount": 0, "dnvotee_count": 0, "self_vote_rate": 7.0, "upvotee": [{"account": "meesterboom", "percentage": 28.9, "rshares": 9518042704124}, {"account": "goldenoakfarm", "percentage": 11.09, "rshares": 3651691838401}, {"account": "gardenlady", "percentage": 7.0, "rshares": 2306020448904}, {"account": "therealpaul", "percentage": 3.44, "rshares": 1131991370467}, {"account": "writeous", "percentage": 3.17, "rshares": 1044904470398}, {"account": "papa-pepper", "percentage": 3.17, "rshares": 1044365760348}, {"account": "karenb54", "percentage": 2.09, "rshares": 687455562344}, {"account": "englishtchrivy", "percentage": 1.59, "rshares": 522401363845}, {"account": "old-guy-photos", "percentage": 1.57, "rshares": 517887326908}, {"account": "petals", "percentage": 1.45, "rshares": 478611334988}], "downvotee": []}, {"start_date": "2018-02-04", "end_date": "2018-04-05", "days": 60, "all_vweight": 757400.0, "plus_rshares": 65457412559595.0, "minus_rshares": 0, "self_rshares": 4906764662666.0, "sum_of_share_squared": 0.08668113645426777, "vcount": 367, "inverse_simpson": 12, "avg_full_voting_per_day": 1.26, "upvcount": 367, "upvotee_count": 147, "dnvcount": 0, "dnvotee_count": 0, "self_vote_rate": 7.5, "upvotee": [{"account": "meesterboom", "percentage": 26.57, "rshares": 17388842053440}, {"account": "gardenlady", "percentage": 7.5, "rshares": 4906764662666}, {"account": "goldenoakfarm", "percentage": 5.58, "rshares": 3651691838401}, {"account": "davidpakman", "percentage": 3.7, "rshares": 2421791760542}, {"account": "karenb54", "percentage": 3.1, "rshares": 2026484633797}, {"account": "papa-pepper", "percentage": 2.7, "rshares": 1765937593322}, {"account": "steemitblog", "percentage": 2.29, "rshares": 1500397150534}, {"account": "ned", "percentage": 1.98, "rshares": 1295250094476}, {"account": "markrmorrisjr", "percentage": 1.87, "rshares": 1222106787434}, {"account": "therealpaul", "percentage": 1.86, "rshares": 1218970915425}], "downvotee": []}, {"start_date": "2018-01-05", "end_date": "2018-04-05", "days": 90, "all_vweight": 1286300.0, "plus_rshares": 111132721023123.0, "minus_rshares": 0, "self_rshares": 10109604164484.0, "sum_of_share_squared": 0.07286396621113764, "vcount": 649, "inverse_simpson": 14, "avg_full_voting_per_day": 1.43, "upvcount": 649, "upvotee_count": 239, "dnvcount": 0, "dnvotee_count": 0, "self_vote_rate": 9.1, "upvotee": [{"account": "meesterboom", "percentage": 23.82, "rshares": 26470458473964}, {"account": "gardenlady", "percentage": 9.1, "rshares": 10109604164484}, {"account": "davidpakman", "percentage": 4.58, "rshares": 5092351439190}, {"account": "goldenoakfarm", "percentage": 3.29, "rshares": 3651691838401}, {"account": "karenb54", "percentage": 2.89, "rshares": 3216963531812}, {"account": "papa-pepper", "percentage": 2.14, "rshares": 2374012898394}, {"account": "markrmorrisjr", "percentage": 1.99, "rshares": 2212886024790}, {"account": "therealpaul", "percentage": 1.41, "rshares": 1562121133175}, {"account": "modernsuperior", "percentage": 1.38, "rshares": 1537732894885}, {"account": "steemitblog", "percentage": 1.35, "rshares": 1500397150534}], "downvotee": []}], "weekly": [{"start_date": "2018-03-29", "end_date": "2018-04-05", "days": 7, "all_vweight": 121000.0, "plus_rshares": 10475660931955.0, "minus_rshares": 0, "self_rshares": 0, "sum_of_share_squared": 0.10631367073012893, "vcount": 47, "inverse_simpson": 9, "avg_full_voting_per_day": 1.73, "upvcount": 47, "upvotee_count": 27, "dnvcount": 0, "dnvotee_count": 0, "self_vote_rate": 0.0, "upvotee": [{"account": "meesterboom", "percentage": 24.98, "rshares": 2616699589334}, {"account": "goldenoakfarm", "percentage": 13.67, "rshares": 1432455374589}, {"account": "therealpaul", "percentage": 9.56, "rshares": 1001425255658}, {"account": "writeous", "percentage": 6.65, "rshares": 696617063065}, {"account": "steemitri", "percentage": 4.11, "rshares": 431044885783}, {"account": "qberryfarms", "percentage": 3.33, "rshares": 348329655732}, {"account": "shadowspub", "percentage": 3.28, "rshares": 343955781021}, {"account": "countrygirl", "percentage": 3.24, "rshares": 339611122132}, {"account": "englishtchrivy", "percentage": 3.24, "rshares": 339611122132}, {"account": "jaybird", "percentage": 2.49, "rshares": 261247241800}], "downvotee": []}, {"start_date": "2018-03-22", "end_date": "2018-03-29", "days": 7, "all_vweight": 88200.0, "plus_rshares": 7668574600984.0, "minus_rshares": 0, "self_rshares": 0, "sum_of_share_squared": 0.14308373590031104, "vcount": 39, "inverse_simpson": 7, "avg_full_voting_per_day": 1.26, "upvcount": 39, "upvotee_count": 24, "dnvcount": 0, "dnvotee_count": 0, "self_vote_rate": 0.0, "upvotee": [{"account": "meesterboom", "percentage": 32.12, "rshares": 2463418542726}, {"account": "goldenoakfarm", "percentage": 13.11, "rshares": 1005295099260}, {"account": "papa-pepper", "percentage": 7.38, "rshares": 565728522029}, {"account": "clio", "percentage": 4.66, "rshares": 356994592516}, {"account": "slowwalker", "percentage": 4.54, "rshares": 348287407333}, {"account": "writeous", "percentage": 4.54, "rshares": 348287407333}, {"account": "kittyandcheese", "percentage": 4.54, "rshares": 348083545393}, {"account": "klye", "percentage": 4.54, "rshares": 348083545393}, {"account": "ericvancewalton", "percentage": 4.48, "rshares": 343933814741}, {"account": "shady", "percentage": 2.84, "rshares": 217584153514}], "downvotee": []}, {"start_date": "2018-03-15", "end_date": "2018-03-22", "days": 7, "all_vweight": 124200.0, "plus_rshares": 10768727307748.0, "minus_rshares": 0, "self_rshares": 2306020448904.0, "sum_of_share_squared": 0.11376642317714614, "vcount": 79, "inverse_simpson": 9, "avg_full_voting_per_day": 1.77, "upvcount": 79, "upvotee_count": 39, "dnvcount": 0, "dnvotee_count": 0, "self_vote_rate": 21.41, "upvotee": [{"account": "gardenlady", "percentage": 21.41, "rshares": 2306020448904}, {"account": "meesterboom", "percentage": 20.65, "rshares": 2223352494829}, {"account": "goldenoakfarm", "percentage": 11.27, "rshares": 1213941364552}, {"account": "petals", "percentage": 4.44, "rshares": 478611334988}, {"account": "papa-pepper", "percentage": 4.04, "rshares": 435098531861}, {"account": "markrmorrisjr", "percentage": 3.27, "rshares": 352434589709}, {"account": "stellabelle", "percentage": 3.23, "rshares": 348083545393}, {"account": "abrockman", "percentage": 3.23, "rshares": 348074105586}, {"account": "old-guy-photos", "percentage": 3.19, "rshares": 343732501075}, {"account": "karenb54", "percentage": 3.15, "rshares": 339381456758}], "downvotee": []}, {"start_date": "2018-03-08", "end_date": "2018-03-15", "days": 7, "all_vweight": 46200.0, "plus_rshares": 4015829875471.0, "minus_rshares": 0, "self_rshares": 0, "sum_of_share_squared": 0.33240735138537375, "vcount": 24, "inverse_simpson": 3, "avg_full_voting_per_day": 0.66, "upvcount": 24, "upvotee_count": 13, "dnvcount": 0, "dnvotee_count": 0, "self_vote_rate": 0.0, "upvotee": [{"account": "meesterboom", "percentage": 55.15, "rshares": 2214572077235}, {"account": "flauwy", "percentage": 8.67, "rshares": 348074105586}, {"account": "karenb54", "percentage": 8.67, "rshares": 348074105586}, {"account": "steembirds", "percentage": 8.67, "rshares": 348074105586}, {"account": "doitvoluntarily", "percentage": 5.42, "rshares": 217521606215}, {"account": "shikharsri", "percentage": 2.17, "rshares": 87018526396}, {"account": "silviabeneforti", "percentage": 2.17, "rshares": 87018526396}, {"account": "hilarski", "percentage": 2.17, "rshares": 87018526396}, {"account": "michaelmorcos", "percentage": 2.17, "rshares": 87018526396}, {"account": "rigaronib", "percentage": 2.17, "rshares": 87018526396}], "downvotee": []}, {"start_date": "2018-03-01", "end_date": "2018-03-08", "days": 7, "all_vweight": 30100.0, "plus_rshares": 2618263780185.0, "minus_rshares": 0, "self_rshares": 869851269088.0, "sum_of_share_squared": 0.29793778640439467, "vcount": 18, "inverse_simpson": 3, "avg_full_voting_per_day": 0.43, "upvcount": 18, "upvotee_count": 14, "dnvcount": 0, "dnvotee_count": 0, "self_vote_rate": 33.22, "upvotee": [{"account": "meesterboom", "percentage": 40.53, "rshares": 1061250727372}, {"account": "gardenlady", "percentage": 33.22, "rshares": 869851269088}, {"account": "aggroed", "percentage": 13.29, "rshares": 347918179834}, {"account": "afrinsultana", "percentage": 6.64, "rshares": 173970253817}, {"account": "transisto", "percentage": 3.32, "rshares": 86985126908}, {"account": "aaeesha", "percentage": 0.33, "rshares": 8699317168}, {"account": "cutiepie", "percentage": 0.33, "rshares": 8699317168}, {"account": "blazing", "percentage": 0.33, "rshares": 8698512690}, {"account": "sardrt", "percentage": 0.33, "rshares": 8698512690}, {"account": "nat-expressions", "percentage": 0.33, "rshares": 8698512690}], "downvotee": []}, {"start_date": "2018-02-22", "end_date": "2018-03-01", "days": 7, "all_vweight": 107900.0, "plus_rshares": 9354650060260.0, "minus_rshares": 0, "self_rshares": 1730892944674.0, "sum_of_share_squared": 0.10493492155853125, "vcount": 62, "inverse_simpson": 10, "avg_full_voting_per_day": 1.54, "upvcount": 62, "upvotee_count": 39, "dnvcount": 0, "dnvotee_count": 0, "self_vote_rate": 18.5, "upvotee": [{"account": "meesterboom", "percentage": 22.41, "rshares": 2096207033497}, {"account": "gardenlady", "percentage": 18.5, "rshares": 1730892944674}, {"account": "steemitblog", "percentage": 6.97, "rshares": 652346587189}, {"account": "markrmorrisjr", "percentage": 5.58, "rshares": 521877269751}, {"account": "ruwan", "percentage": 4.65, "rshares": 434897724792}, {"account": "tamacvet", "percentage": 3.81, "rshares": 356616134329}, {"account": "petals", "percentage": 3.72, "rshares": 347918179834}, {"account": "sardrt", "percentage": 3.72, "rshares": 347918179834}, {"account": "gringalicious", "percentage": 3.72, "rshares": 347918179834}, {"account": "sunscape", "percentage": 3.72, "rshares": 347918179834}], "downvotee": []}, {"start_date": "2018-02-15", "end_date": "2018-02-22", "days": 7, "all_vweight": 58000.0, "plus_rshares": 4992625880608.0, "minus_rshares": 0, "self_rshares": 0, "sum_of_share_squared": 0.18630340297947232, "vcount": 24, "inverse_simpson": 5, "avg_full_voting_per_day": 0.83, "upvcount": 24, "upvotee_count": 14, "dnvcount": 0, "dnvotee_count": 0, "self_vote_rate": 0.0, "upvotee": [{"account": "meesterboom", "percentage": 35.89, "rshares": 1791778626142}, {"account": "steemitblog", "percentage": 16.99, "rshares": 848050563345}, {"account": "surfermarly", "percentage": 8.71, "rshares": 434897724792}, {"account": "tuck-fheman", "percentage": 8.62, "rshares": 430548747544}, {"account": "karenb54", "percentage": 6.88, "rshares": 343569202586}, {"account": "davidpakman", "percentage": 6.79, "rshares": 339220225338}, {"account": "slothicorn", "percentage": 3.48, "rshares": 173959089917}, {"account": "exyle", "percentage": 3.4, "rshares": 169610112669}, {"account": "randystiefer", "percentage": 2.53, "rshares": 126120340189}, {"account": "violetmed", "percentage": 2.53, "rshares": 126120340189}], "downvotee": []}], "account": {"id": 7866, "name": "gardenlady", "json_metadata": "{\"profile\":{\"profile_image\":\"https://i.imgsafe.org/5f4a47c5c0.jpg\",\"about\":\"gardening, gardening tips, gardening how-to, garden photos, garden envy, garden delights, and perhaps other random gardening , giggles, and earthly goings-on.  \",\"cover_image\":\"http://imagizer.imageshack.us/v2/640x480q90/924/mXlz7E.jpg\"}}", "proxy": "", "last_owner_update": "2016-08-09T21:27:42", "last_account_update": "2017-08-15T18:15:30", "created": "2016-05-04T11:48:51", "mined": false, "recovery_account": "steem", "last_account_recovery": "1970-01-01T00:00:00", "reset_account": "null", "comment_count": 0, "lifetime_vote_count": 0, "post_count": 2155, "can_vote": true, "voting_power": 9845, "last_vote_time": "2018-04-05T01:28:33", "balance": "40.079 STEEM", "savings_balance": "0.000 STEEM", "sbd_balance": "8.219 SBD", "sbd_seconds": "8130529191", "sbd_seconds_last_update": "2018-04-03T20:25:42", "sbd_last_interest_payment": "2018-03-22T19:36:51", "savings_sbd_balance": "20.000 SBD", "savings_sbd_seconds": "0", "savings_sbd_seconds_last_update": "2018-01-29T15:49:48", "savings_sbd_last_interest_payment": "1970-01-01T00:00:00", "savings_withdraw_requests": 0, "reward_sbd_balance": "0.018 SBD", "reward_steem_balance": "0.005 STEEM", "reward_vesting_balance": "1115.513003 VESTS", "reward_vesting_steem": "0.547 STEEM", "vesting_shares": "43541206.966733 VESTS", "delegated_vesting_shares": "0.000000 VESTS", "received_vesting_shares": "0.000000 VESTS", "vesting_withdraw_rate": "0.000000 VESTS", "next_vesting_withdrawal": "1969-12-31T23:59:59", "withdrawn": 0, "to_withdraw": 0, "withdraw_routes": 0, "curation_rewards": 524929, "posting_rewards": 15585184, "proxied_vsf_votes": [0, 0, 0, 0], "witnesses_voted_for": 10, "last_post": "2018-04-05T01:24:09", "last_root_post": "2018-03-20T17:45:42", "average_bandwidth": "17296781515", "lifetime_bandwidth": "2672649000000", "last_bandwidth_update": "2018-04-05T01:28:33", "average_market_bandwidth": 1360000000, "lifetime_market_bandwidth": "29270000000", "last_market_bandwidth_update": "2017-10-26T14:18:57", "vesting_balance": "0.000 STEEM", "reputation": "34177136003463", "transfer_history": [], "market_history": [], "post_history": [], "vote_history": [], "other_history": [], "witness_votes": ["abit", "aggroed", "arhag", "jesta", "joseph", "lukestokes.mhth", "pharesim", "roelandp", "smooth.witness", "teamsteem"], "tags_usage": [], "guest_bloggers": []}}